LICENSE.txt
README.rst
setup.cfg
setup.py
src/alan_cli.egg-info/PKG-INFO
src/alan_cli.egg-info/SOURCES.txt
src/alan_cli.egg-info/dependency_links.txt
src/alan_cli.egg-info/entry_points.txt
src/alan_cli.egg-info/requires.txt
src/alan_cli.egg-info/top_level.txt
src/handlers/__init__.py
src/handlers/database_handler.py
src/handlers/news_handler.py
src/program/__init__.py
src/program/main.py