Metadata-Version: 2.1
Name: alan-cli
Version: 0.1.2
Home-page: https://github.com/tikikun/cli_tools
Author: Alan Dao
Author-email: contact@daogiatuan.com
License: MIT
Keywords: cli tool
Requires-Python: >=3.10.0
License-File: LICENSE.txt
